KmeansWithNulls/KmeansWithNulls.py
KmeansWithNulls/__init__.py
resources/__init__.py
kmeanswithnulls-0.1.1.dist-info/LICENSE
kmeanswithnulls-0.1.1.dist-info/METADATA
kmeanswithnulls-0.1.1.dist-info/WHEEL
kmeanswithnulls-0.1.1.dist-info/top_level.txt
kmeanswithnulls-0.1.1.dist-info/RECORD
