Metadata-Version: 2.1
Name: kmeanswithnulls
Version: 0.1.1
Summary: a Python implementation of the KMeans clustering algorithm which includes support for handling missing values in the dataset
Home-page: https://github.com/aasedek/KmeansWithNulls.git
Author: Arthur Sedek
Author-email: arthur.sedek@gmail.com
License-File: LICENSE
Requires-Dist: numpy
